brasilapy/__init__.py
brasilapy/client.py
brasilapy/constants.py
brasilapy/exceptions.py
brasilapy/models/cnpj.py
brasilapy/models/general.py
brasilapy/processor.py
brasilapy/utils.py
brasilapy-1.2.2.dist-info/LICENSE
brasilapy-1.2.2.dist-info/WHEEL
brasilapy-1.2.2.dist-info/METADATA
brasilapy-1.2.2.dist-info/RECORD
